rpa_quaestvm/__init__.py
rpa_quaestvm/cv2_utils.py
rpa_quaestvm/date_utils.py
rpa_quaestvm/env_utils.py
rpa_quaestvm/inicializador.py
rpa_quaestvm/json_utils.py
rpa_quaestvm/logger.py
rpa_quaestvm/metrics.py
rpa_quaestvm/ocr.py
rpa_quaestvm/plyer.py
rpa_quaestvm/pya_utils.py
rpa_quaestvm/pyautoqstvm.py
rpa_quaestvm/requirements.txt
rpa_quaestvm/rpa_exceptions.py
rpa_quaestvm/string_utils.py
rpa_quaestvm/subprocess_utils.py
rpa_quaestvm-1.5.0.dist-info/METADATA
rpa_quaestvm-1.5.0.dist-info/WHEEL
rpa_quaestvm-1.5.0.dist-info/licenses/LICENSE
rpa_quaestvm-1.5.0.dist-info/RECORD
