Metadata-Version: 2.4
Name: rpa_quaestvm
Version: 1.5.0
Summary: Abstrações e utilidades da biblioteca pyautogui e outras ferramentas de RPA
Author-email: Wellington Velasco <wvelasco@quaestum.com.br>, Indira Lima <indira.lima@quaestum.com.br>
License-Expression: MIT
License-File: LICENSE
Classifier: Operating System :: OS Independent
Classifier: Programming Language :: Python :: 3
Requires-Python: >=3.9
Requires-Dist: easyocr
Requires-Dist: opencv-python
Requires-Dist: pillow
Requires-Dist: plyer
Requires-Dist: psutil
Requires-Dist: pyautogui
Requires-Dist: pygetwindow
Requires-Dist: pyscreeze
Requires-Dist: python-dotenv
